primate/__init__.py
primate/i18n.py
primate/pema.py
primate/readable.py
primate/request.py
primate/request_bag.py
primate/request_body.py
primate/response.py
primate/route.py
primate/session.py
primate/type_converter.py
primate/uploaded_file.py
primate/url.py
primate_run-0.4.2.dist-info/METADATA
primate_run-0.4.2.dist-info/WHEEL
primate_run-0.4.2.dist-info/licenses/LICENSE
primate_run-0.4.2.dist-info/RECORD
